Workbook

Sheet Dashboard
C3: Portfolio | K3: Positionen | S3: Dividende
C5: Investition | E5: Aktueller Wert | G5: Dividende gesamt | K5: A0NCFR | S5: Position | T5: 2022 | U5: 2023 | V5: 2024 | W5: 2025 | X5: 2026 | Y5: 2027 | Z5: 2028 | AA5: 2029
C6: =-SUM(Transaktionen!G6:G21) -> 4500 | E6: =M8+M14+M20 -> 9353 | G6: =SUM(Transaktionen!M6:M21) -> 80 | S6: Gesamt | T6: {=SUMPRODUCT(--(YEAR(Transaktionen!$K$6:$K$21)=Dashboard!T$5),Transaktionen!$M$6:$M$21)} -> 0 | U6: {=SUMPRODUCT(--(YEAR(Transaktionen!$K$6:$K$21)=Dashboard!U$5),Transaktionen!$M$6:$M$21)} -> 10 | V6: {=SUMPRODUCT(--(YEAR(Transaktionen!$K$6:$K$21)=Dashboard!V$5),Transaktionen!$M$6:$M$21)} -> 20 | W6: {=SUMPRODUCT(--(YEAR(Transaktionen!$K$6:$K$21)=Dashboard!W$5),Transaktionen!$M$6:$M$21)} -> 20 | X6: {=SUMPRODUCT(--(YEAR(Transaktionen!$K$6:$K$21)=Dashboard!X$5),Transaktionen!$M$6:$M$21)} -> 30 | Y6: {=SUMPRODUCT(--(YEAR(Transaktionen!$K$6:$K$21)=Dashboard!Y$5),Transaktionen!$M$6:$M$21)} -> 0 | Z6: {=SUMPRODUCT(--(YEAR(Transaktionen!$K$6:$K$21)=Dashboard!Z$5),Transaktionen!$M$6:$M$21)} -> 0 | AA6: {=SUMPRODUCT(--(YEAR(Transaktionen!$K$6:$K$21)=Dashboard!AA$5),Transaktionen!$M$6:$M$21)} -> 0
E7: =E6/C6 -> 2.0784444 | G7: =G6/C6 -> 0.017777778 | K7: Investition | M7: Aktueller Wert | O7: Dividende | S7: A0NCFR | T7: {=SUMPRODUCT(--(YEAR(Transaktionen!$K$6:$K$21)=Dashboard!T$5),Transaktionen!$M$6:$M$21,--(Transaktionen!$L$6:$L$21=$S7))} -> 0 | U7: {=SUMPRODUCT(--(YEAR(Transaktionen!$K$6:$K$21)=Dashboard!U$5),Transaktionen!$M$6:$M$21,--(Transaktionen!$L$6:$L$21=$S7))} -> 10 | V7: {=SUMPRODUCT(--(YEAR(Transaktionen!$K$6:$K$21)=Dashboard!V$5),Transaktionen!$M$6:$M$21,--(Transaktionen!$L$6:$L$21=$S7))} -> 10 | W7: {=SUMPRODUCT(--(YEAR(Transaktionen!$K$6:$K$21)=Dashboard!W$5),Transaktionen!$M$6:$M$21,--(Transaktionen!$L$6:$L$21=$S7))} -> 10 | X7: {=SUMPRODUCT(--(YEAR(Transaktionen!$K$6:$K$21)=Dashboard!X$5),Transaktionen!$M$6:$M$21,--(Transaktionen!$L$6:$L$21=$S7))} -> 10 | Y7: {=SUMPRODUCT(--(YEAR(Transaktionen!$K$6:$K$21)=Dashboard!Y$5),Transaktionen!$M$6:$M$21,--(Transaktionen!$L$6:$L$21=$S7))} -> 0 | Z7: {=SUMPRODUCT(--(YEAR(Transaktionen!$K$6:$K$21)=Dashboard!Z$5),Transaktionen!$M$6:$M$21,--(Transaktionen!$L$6:$L$21=$S7))} -> 0 | AA7: {=SUMPRODUCT(--(YEAR(Transaktionen!$K$6:$K$21)=Dashboard!AA$5),Transaktionen!$M$6:$M$21,--(Transaktionen!$L$6:$L$21=$S7))} -> 0
E8: Gewinn | K8: =-SUMIF(Transaktionen!$D$6:$D$21,Dashboard!K5,Transaktionen!$G$6:$G$21) -> 1000 | M8: =_xlfn.XLOOKUP(K5,Portfolio!$D$6:$D$21,Portfolio!$F$6:$F$21)*_xlfn.XLOOKUP(K5,Portfolio!$D$6:$D$21,Portfolio!$H$6:$H$21) -> 3967.6 | O8: =SUMIF(Transaktionen!$L$6:$L$21,Dashboard!K5,Transaktionen!$M$6:$M$21) -> 40 | S8: ETF903 | T8: {=SUMPRODUCT(--(YEAR(Transaktionen!$K$6:$K$21)=Dashboard!T$5),Transaktionen!$M$6:$M$21,--(Transaktionen!$L$6:$L$21=$S8))} -> 0 | U8: {=SUMPRODUCT(--(YEAR(Transaktionen!$K$6:$K$21)=Dashboard!U$5),Transaktionen!$M$6:$M$21,--(Transaktionen!$L$6:$L$21=$S8))} -> 0 | V8: {=SUMPRODUCT(--(YEAR(Transaktionen!$K$6:$K$21)=Dashboard!V$5),Transaktionen!$M$6:$M$21,--(Transaktionen!$L$6:$L$21=$S8))} -> 10 | W8: {=SUMPRODUCT(--(YEAR(Transaktionen!$K$6:$K$21)=Dashboard!W$5),Transaktionen!$M$6:$M$21,--(Transaktionen!$L$6:$L$21=$S8))} -> 10 | X8: {=SUMPRODUCT(--(YEAR(Transaktionen!$K$6:$K$21)=Dashboard!X$5),Transaktionen!$M$6:$M$21,--(Transaktionen!$L$6:$L$21=$S8))} -> 10 | Y8: {=SUMPRODUCT(--(YEAR(Transaktionen!$K$6:$K$21)=Dashboard!Y$5),Transaktionen!$M$6:$M$21,--(Transaktionen!$L$6:$L$21=$S8))} -> 0 | Z8: {=SUMPRODUCT(--(YEAR(Transaktionen!$K$6:$K$21)=Dashboard!Z$5),Transaktionen!$M$6:$M$21,--(Transaktionen!$L$6:$L$21=$S8))} -> 0 | AA8: {=SUMPRODUCT(--(YEAR(Transaktionen!$K$6:$K$21)=Dashboard!AA$5),Transaktionen!$M$6:$M$21,--(Transaktionen!$L$6:$L$21=$S8))} -> 0
E9: =E6-C6 -> 4853 | M9: =M8/K8 -> 3.9676 | O9: =O8/K8 -> 0.04 | S9: DBX0TR | T9: {=SUMPRODUCT(--(YEAR(Transaktionen!$K$6:$K$21)=Dashboard!T$5),Transaktionen!$M$6:$M$21,--(Transaktionen!$L$6:$L$21=$S9))} -> 0 | U9: {=SUMPRODUCT(--(YEAR(Transaktionen!$K$6:$K$21)=Dashboard!U$5),Transaktionen!$M$6:$M$21,--(Transaktionen!$L$6:$L$21=$S9))} -> 0 | V9: {=SUMPRODUCT(--(YEAR(Transaktionen!$K$6:$K$21)=Dashboard!V$5),Transaktionen!$M$6:$M$21,--(Transaktionen!$L$6:$L$21=$S9))} -> 0 | W9: {=SUMPRODUCT(--(YEAR(Transaktionen!$K$6:$K$21)=Dashboard!W$5),Transaktionen!$M$6:$M$21,--(Transaktionen!$L$6:$L$21=$S9))} -> 0 | X9: {=SUMPRODUCT(--(YEAR(Transaktionen!$K$6:$K$21)=Dashboard!X$5),Transaktionen!$M$6:$M$21,--(Transaktionen!$L$6:$L$21=$S9))} -> 10 | Y9: {=SUMPRODUCT(--(YEAR(Transaktionen!$K$6:$K$21)=Dashboard!Y$5),Transaktionen!$M$6:$M$21,--(Transaktionen!$L$6:$L$21=$S9))} -> 0 | Z9: {=SUMPRODUCT(--(YEAR(Transaktionen!$K$6:$K$21)=Dashboard!Z$5),Transaktionen!$M$6:$M$21,--(Transaktionen!$L$6:$L$21=$S9))} -> 0 | AA9: {=SUMPRODUCT(--(YEAR(Transaktionen!$K$6:$K$21)=Dashboard!AA$5),Transaktionen!$M$6:$M$21,--(Transaktionen!$L$6:$L$21=$S9))} -> 0
K11: ETF903
K13: Investition | M13: Aktueller Wert | O13: Dividende
K14: =-SUMIF(Transaktionen!$D$6:$D$21,Dashboard!K11,Transaktionen!$G$6:$G$21) -> 2500 | M14: =_xlfn.XLOOKUP(K11,Portfolio!$D$6:$D$21,Portfolio!$F$6:$F$21)*_xlfn.XLOOKUP(K11,Portfolio!$D$6:$D$21,Portfolio!$H$6:$H$21) -> 4433.6 | O14: =SUMIF(Transaktionen!$L$6:$L$21,Dashboard!K11,Transaktionen!$M$6:$M$21) -> 30
M15: =M14/K14 -> 1.77344 | O15: =O14/K14 -> 0.012
K17: DBX0TR
K19: Investition | M19: Aktueller Wert | O19: Dividende
K20: =-SUMIF(Transaktionen!$D$6:$D$21,Dashboard!K17,Transaktionen!$G$6:$G$21) -> 1000 | M20: =_xlfn.XLOOKUP(K17,Portfolio!$D$6:$D$21,Portfolio!$F$6:$F$21)*_xlfn.XLOOKUP(K17,Portfolio!$D$6:$D$21,Portfolio!$H$6:$H$21) -> 951.8 | O20: =SUMIF(Transaktionen!$L$6:$L$21,Dashboard!K17,Transaktionen!$M$6:$M$21) -> 10
M21: =M20/K20 -> 0.9518 | O21: =O20/K20 -> 0.01

Sheet Portfolio
C3: Positionen | L3: Gewichtung
C5: Bezeichnung | D5: WKN | E5: ISIN | F5: Bestand | G5: Durchschn. Preis p. S. | H5: Aktueller Wert p. S. (€) | L5: WKN | M5: Gesamtanteil | N5: Prozentualer Anteil
C6: UBS (Lux) Fund Solutions - MSCI World UCITS ETF(USD)A-dis | D6: A0NCFR | E6: LU0340285161 | F6: =SUMIF(Transaktionen!$D$6:$D$21,Portfolio!$D6,Transaktionen!$E$6:$E$21) -> 10 | G6: =IF(F6>0,(-SUMIF(Transaktionen!$D$6:$D$21,Portfolio!$D6,Transaktionen!$G$6:$G$21)/F6),0) -> 100 | H6: ='Realtime-Kurse A0NCFR'!B3 -> 396,76 | L6: A0NCFR | M6: =H6*F6 -> 3967.6 | N6: =M6/SUM($M$6:$M$21) -> 0.42420614
C7: Lyxor 1 DivDAX | D7: ETF903 | E7: DE000ETF9033 | F7: =SUMIF(Transaktionen!$D$6:$D$21,Portfolio!$D7,Transaktionen!$E$6:$E$21) -> 20 | G7: =IF(F7>0,(-SUMIF(Transaktionen!$D$6:$D$21,Portfolio!$D7,Transaktionen!$G$6:$G$21)/F7),0) -> 125 | H7: ='Realtime-Kurse ETF903'!B3 -> 221,68 | L7: ETF903 | M7: =H7*F7 -> 4433.6 | N7: =M7/SUM($M$6:$M$21) -> 0.47402972
C8: Xtrackers Stoxx Europe 600 ETF 1D | D8: DBX0TR | E8: LU2581375156 | F8: =SUMIF(Transaktionen!$D$6:$D$21,Portfolio!$D8,Transaktionen!$E$6:$E$21) -> 10 | G8: =IF(F8>0,(-SUMIF(Transaktionen!$D$6:$D$21,Portfolio!$D8,Transaktionen!$G$6:$G$21)/F8),0) -> 100 | H8: ='Realtime-Kurse DBX0TR'!B3 -> 95,18 | L8: DBX0TR | M8: =H8*F8 -> 951.8 | N8: =M8/SUM($M$6:$M$21) -> 0.10176414
F9: =SUMIF(Transaktionen!$D$6:$D$21,Portfolio!$D9,Transaktionen!$E$6:$E$21) -> 0 | G9: =IF(F9>0,(-SUMIF(Transaktionen!$D$6:$D$21,Portfolio!$D9,Transaktionen!$G$6:$G$21)/F9),0) -> 0 | M9: =H9*F9 -> 0 | N9: =M9/SUM($M$6:$M$21) -> 0
F10: =SUMIF(Transaktionen!$D$6:$D$21,Portfolio!$D10,Transaktionen!$E$6:$E$21) -> 0 | G10: =IF(F10>0,(-SUMIF(Transaktionen!$D$6:$D$21,Portfolio!$D10,Transaktionen!$G$6:$G$21)/F10),0) -> 0 | M10: =H10*F10 -> 0 | N10: =M10/SUM($M$6:$M$21) -> 0
F11: =SUMIF(Transaktionen!$D$6:$D$21,Portfolio!$D11,Transaktionen!$E$6:$E$21) -> 0 | G11: =IF(F11>0,(-SUMIF(Transaktionen!$D$6:$D$21,Portfolio!$D11,Transaktionen!$G$6:$G$21)/F11),0) -> 0 | M11: =H11*F11 -> 0 | N11: =M11/SUM($M$6:$M$21) -> 0
F12: =SUMIF(Transaktionen!$D$6:$D$21,Portfolio!$D12,Transaktionen!$E$6:$E$21) -> 0 | G12: =IF(F12>0,(-SUMIF(Transaktionen!$D$6:$D$21,Portfolio!$D12,Transaktionen!$G$6:$G$21)/F12),0) -> 0 | M12: =H12*F12 -> 0 | N12: =M12/SUM($M$6:$M$21) -> 0
F13: =SUMIF(Transaktionen!$D$6:$D$21,Portfolio!$D13,Transaktionen!$E$6:$E$21) -> 0 | G13: =IF(F13>0,(-SUMIF(Transaktionen!$D$6:$D$21,Portfolio!$D13,Transaktionen!$G$6:$G$21)/F13),0) -> 0 | M13: =H13*F13 -> 0 | N13: =M13/SUM($M$6:$M$21) -> 0
F14: =SUMIF(Transaktionen!$D$6:$D$21,Portfolio!$D14,Transaktionen!$E$6:$E$21) -> 0 | G14: =IF(F14>0,(-SUMIF(Transaktionen!$D$6:$D$21,Portfolio!$D14,Transaktionen!$G$6:$G$21)/F14),0) -> 0 | M14: =H14*F14 -> 0 | N14: =M14/SUM($M$6:$M$21) -> 0
F15: =SUMIF(Transaktionen!$D$6:$D$21,Portfolio!$D15,Transaktionen!$E$6:$E$21) -> 0 | G15: =IF(F15>0,(-SUMIF(Transaktionen!$D$6:$D$21,Portfolio!$D15,Transaktionen!$G$6:$G$21)/F15),0) -> 0 | M15: =H15*F15 -> 0 | N15: =M15/SUM($M$6:$M$21) -> 0
F16: =SUMIF(Transaktionen!$D$6:$D$21,Portfolio!$D16,Transaktionen!$E$6:$E$21) -> 0 | G16: =IF(F16>0,(-SUMIF(Transaktionen!$D$6:$D$21,Portfolio!$D16,Transaktionen!$G$6:$G$21)/F16),0) -> 0 | M16: =H16*F16 -> 0 | N16: =M16/SUM($M$6:$M$21) -> 0
F17: =SUMIF(Transaktionen!$D$6:$D$21,Portfolio!$D17,Transaktionen!$E$6:$E$21) -> 0 | G17: =IF(F17>0,(-SUMIF(Transaktionen!$D$6:$D$21,Portfolio!$D17,Transaktionen!$G$6:$G$21)/F17),0) -> 0 | M17: =H17*F17 -> 0 | N17: =M17/SUM($M$6:$M$21) -> 0
F18: =SUMIF(Transaktionen!$D$6:$D$21,Portfolio!$D18,Transaktionen!$E$6:$E$21) -> 0 | G18: =IF(F18>0,(-SUMIF(Transaktionen!$D$6:$D$21,Portfolio!$D18,Transaktionen!$G$6:$G$21)/F18),0) -> 0 | M18: =H18*F18 -> 0 | N18: =M18/SUM($M$6:$M$21) -> 0
F19: =SUMIF(Transaktionen!$D$6:$D$21,Portfolio!$D19,Transaktionen!$E$6:$E$21) -> 0 | G19: =IF(F19>0,(-SUMIF(Transaktionen!$D$6:$D$21,Portfolio!$D19,Transaktionen!$G$6:$G$21)/F19),0) -> 0 | M19: =H19*F19 -> 0 | N19: =M19/SUM($M$6:$M$21) -> 0
F20: =SUMIF(Transaktionen!$D$6:$D$21,Portfolio!$D20,Transaktionen!$E$6:$E$21) -> 0 | G20: =IF(F20>0,(-SUMIF(Transaktionen!$D$6:$D$21,Portfolio!$D20,Transaktionen!$G$6:$G$21)/F20),0) -> 0 | M20: =H20*F20 -> 0 | N20: =M20/SUM($M$6:$M$21) -> 0
F21: =SUMIF(Transaktionen!$D$6:$D$21,Portfolio!$D21,Transaktionen!$E$6:$E$21) -> 0 | G21: =IF(F21>0,(-SUMIF(Transaktionen!$D$6:$D$21,Portfolio!$D21,Transaktionen!$G$6:$G$21)/F21),0) -> 0 | M21: =H21*F21 -> 0 | N21: =M21/SUM($M$6:$M$21) -> 0

Sheet Transaktionen
C3: An-/ Verkauf | K3: Dividende
C5: Datum | D5: Aktie | E5: An-/ Verkauf | F5: Preis p.S. | G5: Gesamtbetrag | K5: Datum | L5: Aktie | M5: Dividende
C6: 44562 | D6: A0NCFR | E6: 10 | F6: 100 | G6: =-F6*E6 -> -1000 | K6: 44927 | L6: A0NCFR | M6: 10
C7: 44927 | D7: ETF903 | E7: 10 | F7: 100 | G7: =-F7*E7 -> -1000 | K7: 45292 | L7: A0NCFR | M7: 10
C8: 45292 | D8: ETF903 | E8: 10 | F8: 150 | G8: =-F8*E8 -> -1500 | K8: 45292 | L8: ETF903 | M8: 10
C9: 45658 | D9: DBX0TR | E9: 10 | F9: 100 | G9: =-F9*E9 -> -1000 | K9: 45658 | L9: A0NCFR | M9: 10
K10: 45658 | L10: ETF903 | M10: 10
K11: 46023 | L11: A0NCFR | M11: 10
K12: 46023 | L12: ETF903 | M12: 10
K13: 46023 | L13: DBX0TR | M13: 10

Sheet Realtime-Kurse A0NCFR
A1: Column1 | B1: Column2 | C1: Column3
A2: Börsenplatz: | B2: L&S RT Düsseldorf Frankfurt Hamburg Hannover München Stuttgart (EUWAX)
A3: aktueller Kurs: | B3: 396,76
A4: Veränderung: | B4: 0,01
A5: Veränderung in %: | B5: 0,00 %

Sheet Realtime-Kurse DBX0TR
A1: Column1 | B1: Column2 | C1: Column3
A2: Börsenplatz: | B2: L&S RT Düsseldorf Frankfurt Hamburg München Stuttgart (EUWAX)
A3: aktueller Kurs: | B3: 95,18
A4: Veränderung: | B4: 0,22
A5: Veränderung in %: | B5: 0,23 %

Sheet Realtime-Kurse ETF903
A1: Column1 | B1: Column2 | C1: Column3
A2: Börsenplatz: | B2: L&S RT Düsseldorf Fondsgesellschaft Frankfurt Hamburg München Stuttgart (EUWAX)
A3: aktueller Kurs: | B3: 221,68
A4: Veränderung: | B4: 0,00
A5: Veränderung in %: | B5: 0,00 %
